servirtium/__init__.py
servirtium/interaction_recording.py
servirtium/interactions.py
servirtium/markdown_parser.py
servirtium/markup.py
servirtium/playback.py
servirtium/recorder.py
test/__init__.py
test/compatibility-suite.py
test/test_markdown_parser.py
test/test_markup.py
test/test_recorder.py
servirtium-0.1.0.dist-info/LICENSE.txt
servirtium-0.1.0.dist-info/METADATA
servirtium-0.1.0.dist-info/WHEEL
servirtium-0.1.0.dist-info/top_level.txt
servirtium-0.1.0.dist-info/RECORD
