Metadata-Version: 2.1
Name: servirtium
Version: 0.1.0
Summary: Servirtium service virtualization
Home-page: https://github.com/servirtium/servirtium-python
Author: Paul Hammant
Author-email: paul@hammant.org
License: UNKNOWN
Platform: UNKNOWN
Requires: requests
Requires: pytest
